<?xml version='1.0' encoding='utf-8'?>
<!-- @(#) $Id: basic.xml 9433 2009-07-14 21:59:08Z yeti-dn $ -->
<!DOCTYPE book PUBLIC '-//OASIS//DTD DocBook XML V4.5//EN'
          'http://www.oasis-open.org/docbook/xml/4.5/docbookx.dtd'>
<informalequation id='eq-height-height-correlation-exponential'>
  <mediaobject>
    <imageobject>
      <imagedata fileref='eq-height-height-correlation-exponential.png' format='PNG'/>
    </imageobject>
    <textobject role='tex'>
      <phrase>
<![CDATA[
H_x(\tau_x) = 2\sigma^2\left[ 1 - \exp\left(-{\tau_x\over T}\right) \right]
]]>
      </phrase>
    </textobject>
  </mediaobject>
</informalequation>
<!-- vim: set ts=2 sw=2 et : -->
